{
    "children": [
        {
            "childDataSource": "CustomerOrders.ttOrder",
            "childGridProperties": {
                "altRowTemplateFunction": "",
                "altRowTemplateId": "",
                "columns": [
                    {
                        "encoded": true,
                        "field": "OrderNum",
                        "filterable": true,
                        "format": "",
                        "sortable": true,
                        "title": "OrderNum"
                    },
                    {
                        "encoded": true,
                        "field": "OrderStatus",
                        "filterable": true,
                        "format": "",
                        "sortable": true,
                        "title": "OrderStatus"
                    },
                    {
                        "encoded": true,
                        "field": "OrderDate",
                        "filterable": true,
                        "format": "{0:d}",
                        "sortable": true,
                        "title": "OrderDate"
                    },
                    {
                        "encoded": true,
                        "field": "Carrier",
                        "filterable": true,
                        "format": "",
                        "sortable": true,
                        "title": "Carrier"
                    }
                ],
                "editOptions": {
                    "allowDelete": true,
                    "allowEdit": true,
                    "allowInsert": true,
                    "batch": true,
                    "rowButtonLabels": {
                        "canceledit": "Cancel",
                        "destroy": "Delete",
                        "edit": "Edit",
                        "update": "Update"
                    },
                    "toolbarButtonLabels": {
                        "cancel": "Cancel changes",
                        "create": "New",
                        "save": "Save changes"
                    }
                },
                "editable": "Inline",
                "events": {
                    "onDataBound": "",
                    "onRowCreate": "",
                    "onRowDelete": "",
                    "onRowSelect": "onChildRowSelect",
                    "onRowUpdate": ""
                },
                "filterable": false,
                "groupable": false,
                "pageSize": 6,
                "reorderable": false,
                "resizable": false,
                "rowTemplateFunction": "",
                "rowTemplateId": "",
                "selectable": "Single",
                "sortable": false,
                "title": "Orders"
            },
            "customSections": {
                "bottom": "bottomSection.html",
                "middle": "middleSection.html",
                "top": "topSection.html",
                "topChild": "topChildSection.html",
                "topParent": "topParentSection.html"
            },
            "dataProvider": "SportsService",
            "events": {
                "hideEventHandler": "onHide",
                "initEventHandler": "onInit",
                "showEventHandler": "onShow"
            },
            "extension": "view-factory.js",
            "extensionFolderName": "Sales/CustOrders",
            "hidden": false,
            "label": "Customer Orders",
            "name": "CustOrders",
            "parentDataSource": "CustomerOrders.ttCustomer",
            "parentGridProperties": {
                "altRowTemplateFunction": "",
                "altRowTemplateId": "",
                "columns": [
                    {
                        "encoded": true,
                        "field": "CustNum",
                        "filterable": true,
                        "format": "",
                        "sortable": true,
                        "title": "CustNum"
                    },
                    {
                        "encoded": true,
                        "field": "Name",
                        "filterable": true,
                        "format": "",
                        "sortable": true,
                        "title": "Name"
                    },
                    {
                        "encoded": true,
                        "field": "Balance",
                        "filterable": true,
                        "format": "{0:c}",
                        "sortable": true,
                        "title": "Balance"
                    },
                    {
                        "encoded": true,
                        "field": "SalesRep",
                        "filterable": true,
                        "format": "",
                        "sortable": true,
                        "title": "SalesRep"
                    }
                ],
                "events": {
                    "onDataBound": "",
                    "onRowSelect": "onParentRowSelect"
                },
                "filterable": false,
                "groupable": true,
                "pageSize": 6,
                "reorderable": false,
                "resizable": false,
                "rowTemplateFunction": "",
                "rowTemplateId": "",
                "sortable": true,
                "title": "Customers"
            },
            "schemaVersion": "1.0",
            "type": "view",
            "uniqueID": "792d09c5-21ec-4d71-9fa9-60d700ecfab6",
            "viewType": "stacked-data-grids"
        },
        {
            "annotations": {
                "dataSources": {
                    "name": "dataSourceName"
                }
            },
            "children": [
                {
                    "annotationRefs": {
                        "dataSourceName": {
                            "kind": "dataSourceName"
                        }
                    },
                    "annotations": {
                        "id": "componentIdentifier"
                    },
                    "containerUid": "628de8ef-425d-4545-b16c-d7c5e4bb0698",
                    "dataSourceName": "Items",
                    "editTemplateFunction": "",
                    "editTemplateId": "",
                    "events": {
                        "onCancel": "",
                        "onChange": "",
                        "onDataBound": "",
                        "onEdit": "",
                        "onRemove": "",
                        "onSave": ""
                    },
                    "id": "itemListview",
                    "model": "ItemsModel",
                    "schemaVersion": "1.0",
                    "selectable": "Single",
                    "templateFunction": "",
                    "templateId": "itemTemplate",
                    "type": "list-view",
                    "uniqueID": "9bf4d282-90a6-43c9-800a-a17e009797f4"
                }
            ],
            "customSections": {
                "top": "topSection.html"
            },
            "dataSources": [
                {
                    "batch": true,
                    "dataProviderName": "SportsService",
                    "dataSourceName": "Item",
                    "name": "Items",
                    "pageSize": 45,
                    "uniqueID": "a4e8893a-455e-4214-b59f-c83486584fca"
                }
            ],
            "events": {
                "hideEventHandler": "onHide",
                "initEventHandler": "onInit",
                "showEventHandler": "onShow"
            },
            "extension": "view-factory.js",
            "extensionFolderName": "Sales/Inventory",
            "hidden": false,
            "label": "Inventory",
            "name": "Inventory",
            "rows": [
                {
                    "cols": [
                        {
                            "breakpoints": {
                                "sm": 12
                            },
                            "hidden": {
                                "lg": false,
                                "md": false,
                                "sm": false,
                                "xs": false
                            },
                            "rows": [],
                            "schemaVersion": "1.0",
                            "type": "col",
                            "uniqueID": "628de8ef-425d-4545-b16c-d7c5e4bb0698"
                        },
                        {
                            "breakpoints": {
                                "sm": 6
                            },
                            "hidden": {
                                "lg": false,
                                "md": false,
                                "sm": false,
                                "xs": false
                            },
                            "rows": [],
                            "schemaVersion": "1.0",
                            "type": "col",
                            "uniqueID": "09637a36-6570-4134-9f99-edcc00984945"
                        }
                    ],
                    "schemaVersion": "1.0",
                    "type": "row",
                    "uniqueID": "d9d5b647-6bb5-42d9-84fc-e3f5ff71c538"
                }
            ],
            "schemaVersion": "1.0",
            "type": "view",
            "uniqueID": "6bffd27a-4e84-413d-a102-dae0f09ba018",
            "viewType": "blank"
        },
        {
            "altRowTemplateFunction": "",
            "altRowTemplateId": "",
            "columns": [
                {
                    "encoded": true,
                    "field": "CustNum",
                    "filterable": true,
                    "format": "",
                    "sortable": true,
                    "template": "<div class='customer-name'>#: CustNum #</div><img src='images/#if (CustNum < 12) {##: CustNum##} else { #unknown#}#.jpg' alt='#: CustNum #'/></img>",
                    "title": "CustNum",
                    "width": 100
                },
                {
                    "encoded": true,
                    "field": "Name",
                    "filterable": true,
                    "format": "",
                    "sortable": true,
                    "title": "Name"
                },
                {
                    "encoded": true,
                    "field": "Address",
                    "filterable": true,
                    "format": "",
                    "sortable": true,
                    "title": "Address"
                },
                {
                    "encoded": true,
                    "field": "State",
                    "filterable": true,
                    "format": "",
                    "sortable": true,
                    "title": "State"
                },
                {
                    "encoded": true,
                    "field": "Phone",
                    "filterable": true,
                    "format": "",
                    "sortable": true,
                    "title": "Phone"
                },
                {
                    "encoded": true,
                    "field": "SalesRep",
                    "filterable": true,
                    "format": "",
                    "sortable": true,
                    "title": "SalesRep"
                },
                {
                    "encoded": true,
                    "field": "Balance",
                    "filterable": true,
                    "format": "{0:c}",
                    "sortable": true,
                    "title": "Balance"
                }
            ],
            "confirmRemove": true,
            "createColumns": [],
            "createGroups": [],
            "customSections": {
                "bottom": "bottomSection.html",
                "middle": "middleSection.html",
                "top": "topSection.html"
            },
            "dataProvider": "SportsService",
            "dataSource": "CustomerOrders.ttCustomer",
            "editMode": "Edit",
            "editTitle": "Edit",
            "events": {
                "hideEventHandler": "onHide",
                "initEventHandler": "onInit",
                "onDataBound": "",
                "onRowSelect": "onRowSelect",
                "showEventHandler": "onShow"
            },
            "extension": "view-factory.js",
            "extensionFolderName": "Sales\\CustomerList",
            "filterable": true,
            "groupable": true,
            "groups": [
                {
                    "fields": [
                        {
                            "componentOptions": {
                                "annotations": {
                                    "id": "componentIdentifier"
                                },
                                "downArrowText": "",
                                "events": {
                                    "onChange": ""
                                },
                                "format": "",
                                "id": "ctl502",
                                "model": "formModel.CustNum",
                                "placeholder": "",
                                "schemaVersion": "1.0",
                                "spinners": false,
                                "step": 1,
                                "title": "CustNum",
                                "type": "integer-text-box",
                                "uniqueID": "3960a6e7-8b6c-4183-8b7c-f77340c3225a",
                                "upArrowText": "",
                                "validation": {
                                    "required": false
                                }
                            },
                            "format": "",
                            "id": "ctl501",
                            "itemType": "field",
                            "label": "CustNum",
                            "name": "CustNum"
                        },
                        {
                            "componentOptions": {
                                "annotations": {
                                    "id": "componentIdentifier"
                                },
                                "debounce": 0,
                                "defaultValue": "",
                                "events": {
                                    "onChange": ""
                                },
                                "format": "",
                                "id": "ctl504",
                                "model": "formModel.Name",
                                "placeholder": "",
                                "schemaVersion": "1.0",
                                "title": "Name",
                                "type": "text-box",
                                "uniqueID": "7547ce2f-a0ad-4b7b-845b-bffa085244dc",
                                "validation": {
                                    "required": false
                                }
                            },
                            "format": "",
                            "id": "ctl503",
                            "itemType": "field",
                            "label": "Name",
                            "name": "Name"
                        },
                        {
                            "componentOptions": {
                                "annotations": {
                                    "id": "componentIdentifier"
                                },
                                "debounce": 0,
                                "defaultValue": "",
                                "events": {
                                    "onChange": ""
                                },
                                "format": "",
                                "id": "ctl506",
                                "model": "formModel.Address",
                                "placeholder": "",
                                "schemaVersion": "1.0",
                                "title": "Address",
                                "type": "text-box",
                                "uniqueID": "5f0dfd93-7c6c-48da-afdf-6fea72f62a6e",
                                "validation": {
                                    "required": false
                                }
                            },
                            "format": "",
                            "id": "ctl505",
                            "itemType": "field",
                            "label": "Address",
                            "name": "Address"
                        },
                        {
                            "componentOptions": {
                                "annotationRefs": {
                                    "dataSourceName": {
                                        "kind": "dataSourceName"
                                    }
                                },
                                "annotations": {
                                    "id": "componentIdentifier"
                                },
                                "dataSourceName": "ttStateFK1DS",
                                "events": {
                                    "onChange": "",
                                    "onFilter": "",
                                    "onSelect": ""
                                },
                                "filter": "None",
                                "format": "",
                                "id": "ctl518",
                                "model": "fkeyModels['ttStateFK1DSModel']",
                                "schemaVersion": "1.0",
                                "textField": "State",
                                "title": "ttStateFK1",
                                "type": "combo-box",
                                "uniqueID": "2c402877-4f23-4c77-8fd0-2530011611cd",
                                "validation": {
                                    "required": false
                                },
                                "valueField": "State",
                                "valuePrimitive": false
                            },
                            "format": "",
                            "id": "ctl517",
                            "itemType": "field",
                            "label": "ttStateFK1",
                            "name": "ttStateFK1"
                        },
                        {
                            "componentOptions": {
                                "annotations": {
                                    "id": "componentIdentifier"
                                },
                                "defaultValue": "",
                                "events": {
                                    "onChange": ""
                                },
                                "format": "",
                                "id": "ctl508",
                                "mask": "(999) 000-0000",
                                "model": "formModel.Phone",
                                "schemaVersion": "1.0",
                                "title": "Phone",
                                "type": "phone-text-box",
                                "uniqueID": "842271d2-01f2-43f1-9f9c-a41bc36150a5",
                                "validation": {
                                    "required": false
                                }
                            },
                            "format": "",
                            "id": "ctl507",
                            "itemType": "field",
                            "label": "Phone",
                            "name": "Phone"
                        },
                        {
                            "componentOptions": {
                                "annotations": {
                                    "id": "componentIdentifier"
                                },
                                "downArrowText": "",
                                "events": {
                                    "onChange": ""
                                },
                                "format": "{0:c}",
                                "id": "ctl512",
                                "model": "formModel.Balance",
                                "placeholder": "",
                                "schemaVersion": "1.0",
                                "spinners": false,
                                "title": "Balance",
                                "type": "currency-text-box",
                                "uniqueID": "36d8e2bc-7f56-4235-a8ae-44bc737a27fd",
                                "upArrowText": "",
                                "validation": {
                                    "required": false
                                }
                            },
                            "format": "{0:c}",
                            "id": "ctl511",
                            "itemType": "field",
                            "label": "Balance",
                            "name": "Balance"
                        },
                        {
                            "componentOptions": {
                                "annotationRefs": {
                                    "dataSourceName": {
                                        "kind": "dataSourceName"
                                    }
                                },
                                "annotations": {
                                    "id": "componentIdentifier"
                                },
                                "dataSourceName": "ttSalesRepFK1DS",
                                "events": {
                                    "onChange": "",
                                    "onFilter": "",
                                    "onSelect": ""
                                },
                                "filter": "None",
                                "format": "",
                                "id": "ctl516",
                                "model": "fkeyModels['ttSalesRepFK1DSModel']",
                                "schemaVersion": "1.0",
                                "textField": "SalesRep",
                                "title": "ttSalesRepFK1",
                                "type": "combo-box",
                                "uniqueID": "10af72f9-059a-40b3-b49e-747b09b8b934",
                                "validation": {
                                    "required": false
                                },
                                "valueField": "SalesRep",
                                "valuePrimitive": false
                            },
                            "format": "",
                            "id": "ctl515",
                            "itemType": "field",
                            "label": "ttSalesRepFK1",
                            "name": "ttSalesRepFK1"
                        }
                    ],
                    "id": "224886cb-5b8b-4092-bba3-86be2042fd0e",
                    "name": "Default Group"
                }
            ],
            "hidden": false,
            "label": "Customers",
            "name": "CustomerList",
            "newTitle": "New",
            "pageSize": 10,
            "reorderable": false,
            "resizable": false,
            "rowTemplateFunction": "",
            "rowTemplateId": "",
            "schemaVersion": "1.0",
            "sortable": true,
            "title": "customers",
            "type": "view",
            "uniqueID": "3ca517a0-fa54-4d70-aa01-c3cf20b8eb4e",
            "viewType": "data-grid-separate-form"
        }
    ],
    "description": "Sales",
    "moduleType": "default",
    "name": "Sales",
    "schemaVersion": "1.0",
    "thumbnail": {
        "background": "#000000",
        "color": "#b5e61d",
        "icon": "fa-edit"
    },
    "type": "module",
    "uniqueID": "dc9e1797-e7ea-4b38-b72e-b49fd598b8a5",
    "order": 4
}